buttervolume/VERSION
buttervolume/__init__.py
buttervolume/btrfs.py
buttervolume/cli.py
buttervolume/plugin.py
buttervolume-3.13.dist-info/licenses/LICENSE
buttervolume-3.13.dist-info/METADATA
buttervolume-3.13.dist-info/WHEEL
buttervolume-3.13.dist-info/entry_points.txt
buttervolume-3.13.dist-info/top_level.txt
buttervolume-3.13.dist-info/RECORD
