Metadata-Version: 2.4
Name: buttervolume
Version: 3.13
Summary: Docker plugin to manage Docker Volumes as BTRFS subvolumes
Home-page: https://github.com/ccomb/buttervolume
Author: Christophe Combelles
Author-email: ccomb@free.fr
License: Apache License, Version 2.0
Classifier: Programming Language :: Python :: 3
Classifier: Development Status :: 5 - Production/Stable
Classifier: Intended Audience :: System Administrators
Classifier: License :: OSI Approved :: Apache Software License
Classifier: Operating System :: POSIX :: Linux
Classifier: Topic :: System :: Clustering
License-File: LICENSE
Requires-Dist: bottle
Requires-Dist: urllib3<3.0,>=2.3.0
Requires-Dist: requests-unixsocket2
Requires-Dist: waitress
Requires-Dist: webtest
Dynamic: author
Dynamic: author-email
Dynamic: classifier
Dynamic: description
Dynamic: home-page
Dynamic: license
Dynamic: license-file
Dynamic: requires-dist
Dynamic: summary
